flake8_future.py
flake8_future-0.2.dist-info/WHEEL
flake8_future-0.2.dist-info/metadata.json
flake8_future-0.2.dist-info/pbr.json
flake8_future-0.2.dist-info/DESCRIPTION.rst
flake8_future-0.2.dist-info/METADATA
flake8_future-0.2.dist-info/RECORD
flake8_future-0.2.dist-info/entry_points.txt
flake8_future-0.2.dist-info/top_level.txt
