Metadata-Version: 2.0
Name: flake8-future
Version: 0.2
Summary: A flake8 plugin to warn when any file is missing certain __future__ imports.
Home-page: https://github.com/kmaglione/flake8-future
Author: Kris Maglione
Author-email: maglione.k@gmail.com
License: MIT
Platform: UNKNOWN
Classifier: Development Status :: 4 - Beta
Classifier: Intended Audience :: Developers
Classifier: License :: OSI Approved :: MIT License
Classifier: Operating System :: OS Independent
Classifier: Programming Language :: Python
Classifier: Topic :: Software Development :: Testing
Classifier: Programming Language :: Python :: 2.7
